{"generated_at": "2026-07-15T15:52:08.612774+05:30", "published_at": "2026-07-15T15:52:12.214876+05:30", "scanning": false, "status_msg": "", "market_open": false, "demo": false, "picks": [{"symbol": "NYKAA", "direction": "LONG", "score": 78.28888888888889, "entry": 329.1, "sentiment": 0.2777777777777778, "why": ["Stacked uptrend (20>50>100 EMA)", "Strong 20d momentum (+17.1%)", "RSI 73 (momentum zone)", "ADX 51 (strong trend)", "Consistent move (13/20 up days)", "Within 5% of 52-week high"], "upside": ["Target 1: Rs 357.25  (+8.55% / 1.8R) - book ~50% here", "Target 2: Rs 383.83  (+16.63% / 3.5R) - trail the rest", "On Rs 10,000: ~30 shares -> +Rs 844 at T1, +Rs 1,642 at T2"], "risks": ["Hard stop: Rs 313.46  (-4.75%) - exit immediately if hit; only Rs 985 at risk on 63 shares", "On Rs 10,000: a stop-out loses about Rs 469", "Idea invalidates if price closes back below VWAP/breakout or the uptrend breaks", "Swing trade: hold days-to-weeks; exit if it closes back below the breakout / 20-EMA"], "fundamentals": {}, "budget": {"capital": 10000, "shares": 30, "pnl_t1": 844, "pnl_t2": 1642, "pnl_stop": -469}}, {"symbol": "JBCHEPHARM", "direction": "LONG", "score": 72.73333333333333, "entry": 2506.0, "sentiment": 0.16666666666666666, "why": ["Stacked uptrend (20>50>100 EMA)", "Strong 20d momentum (+14.1%)", "20-day breakout (new high)", "Volume surge (>1.5x avg)", "ADX 41 (strong trend)", "Consistent move (15/20 up days)"], "upside": ["Target 1: Rs 2690.87  (+7.38% / 1.8R) - book ~50% here", "Target 2: Rs 2865.46  (+14.34% / 3.5R) - trail the rest", "On Rs 10,000: ~3 shares -> +Rs 555 at T1, +Rs 1,078 at T2"], "risks": ["Hard stop: Rs 2403.30  (-4.10%) - exit immediately if hit; only Rs 924 at risk on 9 shares", "On Rs 10,000: a stop-out loses about Rs 308", "Idea invalidates if price closes back below VWAP/breakout or the uptrend breaks", "Swing trade: hold days-to-weeks; exit if it closes back below the breakout / 20-EMA"], "fundamentals": {"market_cap": 40220.0, "pe": 56.0, "roe": 18.9}, "budget": {"capital": 10000, "shares": 3, "pnl_t1": 555, "pnl_t2": 1078, "pnl_stop": -308}}, {"symbol": "VEDL", "direction": "SHORT", "score": 68.22222222222223, "entry": 260.55, "sentiment": 0.05555555555555555, "why": ["Stacked downtrend (20<50<100 EMA)", "Strong 20d down-momentum (-15.0%)", "20-day breakdown (new low)", "RSI 28 (weak)", "ADX 34 (strong trend)", "Consistent weakness (13/20 down days)"], "upside": ["Target 1: Rs 237.10  (+9.00% / 1.8R) - book ~50% here", "Target 2: Rs 214.95  (+17.50% / 3.5R) - trail the rest", "On Rs 10,000: ~38 shares -> +Rs 891 at T1, +Rs 1,733 at T2"], "risks": ["Hard stop: Rs 273.58  (-5.00%) - exit immediately if hit; only Rs 990 at risk on 76 shares", "On Rs 10,000: a stop-out loses about Rs 495", "Idea invalidates if price reclaims VWAP or the downtrend breaks", "Swing trade: hold days-to-weeks; exit if it closes back below the breakout / 20-EMA"], "fundamentals": {"market_cap": 101905.0, "pe": 7.64, "roe": 17.3}, "budget": {"capital": 10000, "shares": 38, "pnl_t1": 891, "pnl_t2": 1733, "pnl_stop": -495}}, {"symbol": "OFSS", "direction": "LONG", "score": 67.38888888888889, "entry": 11625.0, "sentiment": 0.2777777777777778, "why": ["Stacked uptrend (20>50>100 EMA)", "Strong 20d momentum (+23.1%)", "RSI 72 (momentum zone)", "ADX 32 (strong trend)", "Within 5% of 52-week high", "Aligned with market regime"], "upside": ["Target 1: Rs 12671.25  (+9.00% / 1.8R) - book ~50% here", "Target 2: Rs 13659.38  (+17.50% / 3.5R) - trail the rest", "On Rs 10,000: ~0 shares -> +Rs 0 at T1, +Rs 0 at T2"], "risks": ["Hard stop: Rs 11043.75  (-5.00%) - exit immediately if hit; only Rs 581 at risk on 1 shares", "On Rs 10,000: a stop-out loses about Rs 0", "Idea invalidates if price closes back below VWAP/breakout or the uptrend breaks", "Swing trade: hold days-to-weeks; exit if it closes back below the breakout / 20-EMA"], "fundamentals": {"market_cap": 101526.0, "pe": 36.6, "roe": 38.1}, "budget": {"capital": 10000, "shares": 0, "pnl_t1": 0, "pnl_t2": 0, "pnl_stop": 0}}, {"symbol": "DIVISLAB", "direction": "LONG", "score": 66.77777777777777, "entry": 7273.0, "sentiment": 0.05555555555555555, "why": ["Stacked uptrend (20>50>100 EMA)", "20-day breakout (new high)", "Volume surge (>1.5x avg)", "RSI 74 (momentum zone)", "ADX 29 (strong trend)", "Within 5% of 52-week high"], "upside": ["Target 1: Rs 7822.58  (+7.56% / 1.8R) - book ~50% here", "Target 2: Rs 8341.64  (+14.69% / 3.5R) - trail the rest", "On Rs 10,000: ~1 shares -> +Rs 550 at T1, +Rs 1,069 at T2"], "risks": ["Hard stop: Rs 6967.68  (-4.20%) - exit immediately if hit; only Rs 916 at risk on 3 shares", "On Rs 10,000: a stop-out loses about Rs 305", "Idea invalidates if price closes back below VWAP/breakout or the uptrend breaks", "Swing trade: hold days-to-weeks; exit if it closes back below the breakout / 20-EMA"], "fundamentals": {"market_cap": 193925.0, "pe": 72.8, "roe": 16.8}, "budget": {"capital": 10000, "shares": 1, "pnl_t1": 550, "pnl_t2": 1069, "pnl_stop": -305}}, {"symbol": "HFCL", "direction": "LONG", "score": 63.93333333333334, "entry": 223.08, "sentiment": 0.16666666666666666, "why": ["Stacked uptrend (20>50>100 EMA)", "Strong 20d momentum (+17.3%)", "RSI 64 (momentum zone)", "ADX 38 (strong trend)", "Within 5% of 52-week high", "Bearish divergence - new high, weaker momentum"], "upside": ["Target 1: Rs 243.16  (+9.00% / 1.8R) - book ~50% here", "Target 2: Rs 262.12  (+17.50% / 3.5R) - trail the rest", "On Rs 10,000: ~44 shares -> +Rs 884 at T1, +Rs 1,718 at T2"], "risks": ["Hard stop: Rs 211.93  (-5.00%) - exit immediately if hit; only Rs 993 at risk on 89 shares", "On Rs 10,000: a stop-out loses about Rs 491", "Idea invalidates if price closes back below VWAP/breakout or the uptrend breaks", "Swing trade: hold days-to-weeks; exit if it closes back below the breakout / 20-EMA"], "fundamentals": {}, "budget": {"capital": 10000, "shares": 44, "pnl_t1": 884, "pnl_t2": 1718, "pnl_stop": -491}}, {"symbol": "TORNTPHARM", "direction": "LONG", "score": 63.08888888888889, "entry": 5017.8, "sentiment": 0.2777777777777778, "why": ["Stacked uptrend (20>50>100 EMA)", "Strong 20d momentum (+12.9%)", "20-day breakout (new high)", "ADX 37 (strong trend)", "Consistent move (16/20 up days)", "Within 5% of 52-week high"], "upside": ["Target 1: Rs 5390.47  (+7.43% / 1.8R) - book ~50% here", "Target 2: Rs 5742.44  (+14.44% / 3.5R) - trail the rest", "On Rs 10,000: ~1 shares -> +Rs 373 at T1, +Rs 725 at T2"], "risks": ["Hard stop: Rs 4810.76  (-4.13%) - exit immediately if hit; only Rs 828 at risk on 4 shares", "On Rs 10,000: a stop-out loses about Rs 207", "Idea invalidates if price closes back below VWAP/breakout or the uptrend breaks", "Swing trade: hold days-to-weeks; exit if it closes back below the breakout / 20-EMA"], "fundamentals": {"market_cap": 168546.0, "pe": 76.2, "roe": 27.6}, "budget": {"capital": 10000, "shares": 1, "pnl_t1": 373, "pnl_t2": 725, "pnl_stop": -207}}, {"symbol": "TATAELXSI", "direction": "SHORT", "score": 60.28888888888889, "entry": 3520.4, "sentiment": 0.2222222222222222, "why": ["Stacked downtrend (20<50<100 EMA)", "Strong 20d down-momentum (-14.0%)", "20-day breakdown (new low)", "Volume surge (>1.5x avg)", "RSI 33 (weak)", "ADX 32 (strong trend)"], "upside": ["Target 1: Rs 3203.56  (+9.00% / 1.8R) - book ~50% here", "Target 2: Rs 2904.33  (+17.50% / 3.5R) - trail the rest", "On Rs 10,000: ~2 shares -> +Rs 634 at T1, +Rs 1,232 at T2"], "risks": ["Hard stop: Rs 3696.42  (-5.00%) - exit immediately if hit; only Rs 880 at risk on 5 shares", "On Rs 10,000: a stop-out loses about Rs 352", "Idea invalidates if price reclaims VWAP or the downtrend breaks", "Swing trade: hold days-to-weeks; exit if it closes back below the breakout / 20-EMA"], "fundamentals": {}, "budget": {"capital": 10000, "shares": 2, "pnl_t1": 634, "pnl_t2": 1232, "pnl_stop": -352}}, {"symbol": "PAYTM", "direction": "LONG", "score": 59.83333333333334, "entry": 1368.0, "sentiment": 0.16666666666666666, "why": ["Stacked uptrend (20>50>100 EMA)", "Strong 20d momentum (+22.1%)", "RSI 76 (momentum zone)", "ADX 33 (strong trend)", "Within 5% of 52-week high", "Overbought RSI 76 - up-move stretched"], "upside": ["Target 1: Rs 1491.12  (+9.00% / 1.8R) - book ~50% here", "Target 2: Rs 1607.40  (+17.50% / 3.5R) - trail the rest", "On Rs 10,000: ~7 shares -> +Rs 862 at T1, +Rs 1,676 at T2"], "risks": ["Hard stop: Rs 1299.60  (-5.00%) - exit immediately if hit; only Rs 958 at risk on 14 shares", "On Rs 10,000: a stop-out loses about Rs 479", "Idea invalidates if price closes back below VWAP/breakout or the uptrend breaks", "Swing trade: hold days-to-weeks; exit if it closes back below the breakout / 20-EMA"], "fundamentals": {}, "budget": {"capital": 10000, "shares": 7, "pnl_t1": 862, "pnl_t2": 1676, "pnl_stop": -479}}, {"symbol": "APOLLOHOSP", "direction": "LONG", "score": 55.111111111111114, "entry": 8934.0, "sentiment": 0.2222222222222222, "why": ["Stacked uptrend (20>50>100 EMA)", "Volume surge (>1.5x avg)", "RSI 69 (momentum zone)", "ADX 32 (strong trend)", "Within 5% of 52-week high", "Aligned with market regime"], "upside": ["Target 1: Rs 9441.63  (+5.68% / 1.8R) - book ~50% here", "Target 2: Rs 9921.06  (+11.05% / 3.5R) - trail the rest", "On Rs 10,000: ~1 shares -> +Rs 508 at T1, +Rs 987 at T2"], "risks": ["Hard stop: Rs 8651.98  (-3.16%) - exit immediately if hit; only Rs 846 at risk on 3 shares", "On Rs 10,000: a stop-out loses about Rs 282", "Idea invalidates if price closes back below VWAP/breakout or the uptrend breaks", "Swing trade: hold days-to-weeks; exit if it closes back below the breakout / 20-EMA"], "fundamentals": {"market_cap": 128455.0, "pe": 85.5, "roe": 16.1}, "budget": {"capital": 10000, "shares": 1, "pnl_t1": 508, "pnl_t2": 987, "pnl_stop": -282}}], "new_picks": [], "locked_today": ["OFSS", "SUNPHARMA", "VEDL", "TATAELXSI", "HFCL", "APOLLOHOSP", "PAYTM", "LUPIN"], "paper": {"summary": {"open": 65, "closed": 24, "win_rate_pct": 4.2, "total_pnl": -20144.85, "expectancy_R": -0.896, "avg_win": 505.08, "best": 505.08, "worst": -999.92}, "equity": [-257.25, -614.55, -109.47, -456.91, -1455.71, -2446.81, -3443.41, -4396.87, -5370.8, -6353.0, -7328.65, -8311.25, -9282.0, -10272.29, -11226.49, -12226.41, -13224.22, -14217.62, -15214.98, -16178.14, -17172.64, -18160.22, -19146.22, -20144.85], "trades": [{"symbol": "LUPIN", "direction": "LONG", "entry": 2503.5, "status": "OPEN", "outcome": 0.0, "pnl": 0.0, "r": 0.0}, {"symbol": "PAYTM", "direction": "LONG", "entry": 1364.8, "status": "OPEN", "outcome": 0.0, "pnl": 0.0, "r": 0.0}, {"symbol": "APOLLOHOSP", "direction": "LONG", "entry": 8977.5, "status": "OPEN", "outcome": 0.0, "pnl": 0.0, "r": 0.0}, {"symbol": "HFCL", "direction": "LONG", "entry": 223.41, "status": "OPEN", "outcome": 0.0, "pnl": 0.0, "r": 0.0}, {"symbol": "TATAELXSI", "direction": "SHORT", "entry": 3517.3, "status": "OPEN", "outcome": 0.0, "pnl": 0.0, "r": 0.0}, {"symbol": "VEDL", "direction": "SHORT", "entry": 263.2, "status": "OPEN", "outcome": 0.0, "pnl": 0.0, "r": 0.0}, {"symbol": "SUNPHARMA", "direction": "LONG", "entry": 1956.2, "status": "OPEN", "outcome": 0.0, "pnl": 0.0, "r": 0.0}, {"symbol": "OFSS", "direction": "LONG", "entry": 11701.0, "status": "OPEN", "outcome": 0.0, "pnl": 0.0, "r": 0.0}, {"symbol": "SONACOMS", "direction": "LONG", "entry": 668.35, "status": "OPEN", "outcome": 0.0, "pnl": 0.0, "r": 0.0}, {"symbol": "KPITTECH", "direction": "SHORT", "entry": 560.45, "status": "OPEN", "outcome": 0.0, "pnl": 0.0, "r": 0.0}, {"symbol": "TORNTPHARM", "direction": "LONG", "entry": 4994.3, "status": "OPEN", "outcome": 0.0, "pnl": 0.0, "r": 0.0}, {"symbol": "JBCHEPHARM", "direction": "LONG", "entry": 2480.7, "status": "OPEN", "outcome": 0.0, "pnl": 0.0, "r": 0.0}, {"symbol": "LAURUSLABS", "direction": "LONG", "entry": 1567.9, "status": "OPEN", "outcome": 0.0, "pnl": 0.0, "r": 0.0}, {"symbol": "OFSS", "direction": "LONG", "entry": 11838.0, "status": "OPEN", "outcome": 0.0, "pnl": 0.0, "r": 0.0}, {"symbol": "KAJARIACER", "direction": "LONG", "entry": 1235.1, "status": "OPEN", "outcome": 0.0, "pnl": 0.0, "r": 0.0}]}, "today_pnl": {"capital": 10000, "closed": 0, "open": 8, "total_pnl": 0.0, "pct": 0.0, "rows": []}, "today_mtm": {"capital_per_trade": 10000, "n": 8, "invested": 80000, "total_pnl": -78.83, "pct": -0.1, "goal_pct": 1, "rows": [{"symbol": "VEDL", "direction": "SHORT", "entry": 263.2, "current": 260.55, "move_pct": 1.01, "pnl": 100.68, "status": "OPEN", "outcome": 0.0}, {"symbol": "PAYTM", "direction": "LONG", "entry": 1364.8, "current": 1368.0, "move_pct": 0.23, "pnl": 23.45, "status": "OPEN", "outcome": 0.0}, {"symbol": "TATAELXSI", "direction": "SHORT", "entry": 3517.3, "current": 3520.4, "move_pct": -0.09, "pnl": -8.81, "status": "OPEN", "outcome": 0.0}, {"symbol": "HFCL", "direction": "LONG", "entry": 223.41, "current": 223.08, "move_pct": -0.15, "pnl": -14.77, "status": "OPEN", "outcome": 0.0}, {"symbol": "SUNPHARMA", "direction": "LONG", "entry": 1956.2, "current": 1951.5, "move_pct": -0.24, "pnl": -24.03, "status": "OPEN", "outcome": 0.0}, {"symbol": "LUPIN", "direction": "LONG", "entry": 2503.5, "current": 2493.0, "move_pct": -0.42, "pnl": -41.94, "status": "OPEN", "outcome": 0.0}, {"symbol": "APOLLOHOSP", "direction": "LONG", "entry": 8977.5, "current": 8934.0, "move_pct": -0.48, "pnl": -48.45, "status": "OPEN", "outcome": 0.0}, {"symbol": "OFSS", "direction": "LONG", "entry": 11701.0, "current": 11625.0, "move_pct": -0.65, "pnl": -64.95, "status": "OPEN", "outcome": 0.0}]}, "today_peak": 0.0, "new_today": {"capital_per_trade": 10000, "n": 0, "invested": 0, "total_pnl": 0.0, "pct": 0.0, "rows": []}, "history": [{"date": "2026-07-14", "picks": 7, "total_pnl": -163.46, "pct": -0.23, "peak_pct": 0.0, "win_rate_pct": 28.6, "best_sym": "KPITTECH", "best_pnl": 86.54, "worst_sym": "OFSS", "worst_pnl": -162.19, "notes": "Reviewed 7 picks: 2 up, 5 down (-0.23% on the day). Winners avg score 65.1 vs losers 66.9; winners 50% trend-aligned vs losers 100%. Losses look like normal market noise, not a systematic mistake. Auto-tuned for tomorrow: min_score 53->54 (win rate 29% / stop-heavy)."}, {"date": "2026-07-13", "picks": 8, "total_pnl": -29.36, "pct": -0.04, "peak_pct": 0.0, "win_rate_pct": 62.5, "best_sym": "PAYTM", "best_pnl": 98.32, "worst_sym": "OFSS", "worst_pnl": -121.11, "notes": "Reviewed 8 picks: 5 up, 3 down (-0.04% on the day). Winners avg score 64.6 vs losers 76.2; winners 100% trend-aligned vs losers 67%. 1 of 3 losers FOUGHT the market regime (up market) - trust the regime more. Auto-tuned for tomorrow: counter_trend_penalty 14->16 (counter-trend picks kept losing)."}, {"date": "2026-07-10", "picks": 8, "total_pnl": 270.17, "pct": 0.34, "peak_pct": 0.0, "win_rate_pct": 62.5, "best_sym": "OFSS", "best_pnl": 121.62, "worst_sym": "DIXON", "worst_pnl": -79.1, "notes": "Reviewed 8 picks: 5 up, 3 down (+0.34% on the day). Winners avg score 72.0 vs losers 70.3; winners 100% trend-aligned vs losers 67%. 1 of 3 losers FOUGHT the market regime (up market) - trust the regime more. Auto-tuned for tomorrow: counter_trend_penalty 12->14 (counter-trend picks kept losing)."}, {"date": "2026-07-09", "picks": 8, "total_pnl": -93.92, "pct": -0.12, "peak_pct": 0.0, "win_rate_pct": 50.0, "best_sym": "DELHIVERY", "best_pnl": 18.46, "worst_sym": "OFSS", "worst_pnl": -58.93, "notes": "Reviewed 8 picks: 4 up, 4 down (-0.12% on the day). Winners avg score 74.0 vs losers 72.8; winners 100% trend-aligned vs losers 100%. Losses look like normal market noise, not a systematic mistake. No threshold change needed - today was within normal range."}, {"date": "2026-07-08", "picks": 8, "total_pnl": -1764.61, "pct": -2.21, "peak_pct": 0.0, "win_rate_pct": 0.0, "best_sym": "OFSS", "best_pnl": -55.14, "worst_sym": "CHOLAFIN", "worst_pnl": -420.66, "notes": "Reviewed 8 picks: 0 up, 8 down (-2.21% on the day). 8 of 8 losers FOUGHT the market regime (down market) - trust the regime more. Auto-tuned for tomorrow: counter_trend_penalty 10->12 (counter-trend picks kept losing); min_score 52->53 (win rate 0% / stop-heavy)."}, {"date": "2026-07-07", "picks": 8, "total_pnl": 409.3, "pct": 0.51, "peak_pct": 0.0, "win_rate_pct": 75.0, "best_sym": "HFCL", "best_pnl": 307.81, "worst_sym": "SHRIRAMFIN", "worst_pnl": -51.29, "notes": "Reviewed 8 picks: 6 up, 2 down (+0.51% on the day). Winners avg score 74.8 vs losers 85.0; winners 100% trend-aligned vs losers 100%. Losses look like normal market noise, not a systematic mistake. Auto-tuned for tomorrow: min_score 53->52 (strong day (win 75%))."}, {"date": "2026-07-06", "picks": 8, "total_pnl": 258.54, "pct": 0.32, "peak_pct": 0.0, "win_rate_pct": 87.5, "best_sym": "CHOLAFIN", "best_pnl": 96.02, "worst_sym": "AUBANK", "worst_pnl": -56.21, "notes": "Reviewed 8 picks: 7 up, 1 down (+0.32% on the day). Winners avg score 85.7 vs losers 74.4; winners 100% trend-aligned vs losers 100%. Losses look like normal market noise, not a systematic mistake. Winners scored higher on average (85.7) than losers (74.4) - demanding a higher score should help. Auto-tuned for tomorrow: min_score 52->53 (winners scored 85.7 vs losers 74.4)."}, {"date": "2026-07-03", "picks": 8, "total_pnl": -410.98, "pct": -0.51, "peak_pct": 0.0, "win_rate_pct": 0.0, "best_sym": "ICICIBANK", "best_pnl": -13.44, "worst_sym": "SHRIRAMFIN", "worst_pnl": -101.44, "notes": "Reviewed 8 picks: 0 up, 8 down (-0.51% on the day). Losses look like normal market noise, not a systematic mistake. Auto-tuned for tomorrow: min_score 51->52 (win rate 0% / stop-heavy)."}, {"date": "2026-07-02", "picks": 6, "total_pnl": -233.7, "pct": -0.39, "peak_pct": 0.0, "win_rate_pct": 33.3, "best_sym": "NYKAA", "best_pnl": 89.97, "worst_sym": "FINCABLES", "worst_pnl": -140.5, "notes": "Reviewed 6 picks: 2 up, 4 down (-0.39% on the day). Winners avg score 73.8 vs losers 63.7; winners 100% trend-aligned vs losers 100%. Losses look like normal market noise, not a systematic mistake. Winners scored higher on average (73.8) than losers (63.7) - demanding a higher score should help. Auto-tuned for tomorrow: min_score 50->51 (winners scored 73.8 vs losers 63.7)."}, {"date": "2026-06-30", "picks": 12, "total_pnl": 1547.88, "pct": 1.29, "peak_pct": 0.2, "win_rate_pct": 75.0, "best_sym": "KPITTECH", "best_pnl": 472.44, "worst_sym": "MAXHEALTH", "worst_pnl": -119.43, "notes": "Reviewed 12 picks: 9 up, 3 down (+1.29% on the day). Winners avg score 58.3 vs losers 76.0; winners 11% trend-aligned vs losers 100%. Losses look like normal market noise, not a systematic mistake. Auto-tuned for tomorrow: min_score 48->47 (strong day (win 75%))."}, {"date": "2026-06-29", "picks": 4, "total_pnl": 81.29, "pct": 0.2, "peak_pct": 0.2, "win_rate_pct": 75.0, "best_sym": "SOUTHBANK", "best_pnl": 94.69, "worst_sym": "OFSS", "worst_pnl": -91.12, "notes": "Reviewed 4 picks: 3 up, 1 down (+0.20% on the day). Losses look like normal market noise, not a systematic mistake. Auto-tuned for tomorrow: min_score 49->48 (strong day (win 75%))."}], "portfolio": {"capital_per_trade": 10000, "n_open": 65, "n_closed": 24, "invested_open": 650000, "invested_total": 890000, "realized_pnl": -9698.31, "unrealized_pnl": 4632.0, "total_pnl": -5066.31, "total_pct": -0.57, "win_rate_pct": 4.2, "lived_up": 1, "lived_up_pct": 4.2, "open": [{"symbol": "PAYTM", "direction": "LONG", "entry": 1263.6, "current": 1368.0, "pnl": 826.21, "ret_pct": 8.26, "logged_at": "2026-07-09"}, {"symbol": "OFSS", "direction": "LONG", "entry": 10974.5, "current": 11625.0, "pnl": 592.74, "ret_pct": 5.93, "logged_at": "2026-06-29"}, {"symbol": "JBCHEPHARM", "direction": "LONG", "entry": 2368.0, "current": 2506.0, "pnl": 582.77, "ret_pct": 5.83, "logged_at": "2026-07-03"}, {"symbol": "NYKAA", "direction": "LONG", "entry": 311.2, "current": 329.1, "pnl": 575.19, "ret_pct": 5.75, "logged_at": "2026-07-02"}, {"symbol": "NYKAA", "direction": "LONG", "entry": 312.8, "current": 329.1, "pnl": 521.1, "ret_pct": 5.21, "logged_at": "2026-07-06"}, {"symbol": "OFSS", "direction": "LONG", "entry": 11063.0, "current": 11625.0, "pnl": 508.0, "ret_pct": 5.08, "logged_at": "2026-07-08"}, {"symbol": "VEDL", "direction": "SHORT", "entry": 273.45, "current": 260.55, "pnl": 471.75, "ret_pct": 4.72, "logged_at": "2026-06-30"}, {"symbol": "NYKAA", "direction": "LONG", "entry": 314.3, "current": 329.1, "pnl": 470.89, "ret_pct": 4.71, "logged_at": "2026-07-07"}, {"symbol": "OFSS", "direction": "LONG", "entry": 11200.0, "current": 11625.0, "pnl": 379.46, "ret_pct": 3.79, "logged_at": "2026-07-09"}, {"symbol": "JBCHEPHARM", "direction": "LONG", "entry": 2418.0, "current": 2506.0, "pnl": 363.94, "ret_pct": 3.64, "logged_at": "2026-07-07"}, {"symbol": "KAJARIACER", "direction": "LONG", "entry": 1196.6, "current": 1237.0, "pnl": 337.62, "ret_pct": 3.38, "logged_at": "2026-06-29"}, {"symbol": "GODREJPROP", "direction": "LONG", "entry": 2036.8, "current": 2104.4, "pnl": 331.89, "ret_pct": 3.32, "logged_at": "2026-07-06"}, {"symbol": "GODREJPROP", "direction": "LONG", "entry": 2038.8, "current": 2104.4, "pnl": 321.76, "ret_pct": 3.22, "logged_at": "2026-07-09"}, {"symbol": "VEDL", "direction": "SHORT", "entry": 269.15, "current": 260.55, "pnl": 319.52, "ret_pct": 3.2, "logged_at": "2026-07-13"}, {"symbol": "JBCHEPHARM", "direction": "LONG", "entry": 2444.2, "current": 2506.0, "pnl": 252.84, "ret_pct": 2.53, "logged_at": "2026-07-13"}, {"symbol": "NYKAA", "direction": "LONG", "entry": 322.7, "current": 329.1, "pnl": 198.33, "ret_pct": 1.98, "logged_at": "2026-07-08"}, {"symbol": "KPITTECH", "direction": "SHORT", "entry": 560.8, "current": 551.6, "pnl": 164.05, "ret_pct": 1.64, "logged_at": "2026-07-10"}, {"symbol": "NYKAA", "direction": "LONG", "entry": 323.9, "current": 329.1, "pnl": 160.54, "ret_pct": 1.61, "logged_at": "2026-07-09"}, {"symbol": "KPITTECH", "direction": "SHORT", "entry": 560.45, "current": 551.6, "pnl": 157.91, "ret_pct": 1.58, "logged_at": "2026-07-14"}, {"symbol": "FEDERALBNK", "direction": "LONG", "entry": 324.05, "current": 327.55, "pnl": 108.01, "ret_pct": 1.08, "logged_at": "2026-06-29"}, {"symbol": "JBCHEPHARM", "direction": "LONG", "entry": 2480.7, "current": 2506.0, "pnl": 101.99, "ret_pct": 1.02, "logged_at": "2026-07-14"}, {"symbol": "VEDL", "direction": "SHORT", "entry": 263.2, "current": 260.55, "pnl": 100.68, "ret_pct": 1.01, "logged_at": "2026-07-15"}, {"symbol": "OFSS", "direction": "LONG", "entry": 11511.0, "current": 11625.0, "pnl": 99.04, "ret_pct": 0.99, "logged_at": "2026-07-10"}, {"symbol": "DIXON", "direction": "LONG", "entry": 13528.0, "current": 13651.0, "pnl": 90.92, "ret_pct": 0.91, "logged_at": "2026-07-10"}, {"symbol": "SUNPHARMA", "direction": "LONG", "entry": 1937.0, "current": 1951.5, "pnl": 74.86, "ret_pct": 0.75, "logged_at": "2026-07-09"}, {"symbol": "NYKAA", "direction": "LONG", "entry": 326.7, "current": 329.1, "pnl": 73.46, "ret_pct": 0.73, "logged_at": "2026-07-10"}, {"symbol": "CHOLAFIN", "direction": "LONG", "entry": 1791.7, "current": 1803.9, "pnl": 68.09, "ret_pct": 0.68, "logged_at": "2026-07-09"}, {"symbol": "SONACOMS", "direction": "LONG", "entry": 665.3, "current": 669.2, "pnl": 58.62, "ret_pct": 0.59, "logged_at": "2026-07-10"}, {"symbol": "TORNTPHARM", "direction": "LONG", "entry": 4994.3, "current": 5017.8, "pnl": 47.05, "ret_pct": 0.47, "logged_at": "2026-07-14"}, {"symbol": "CHOLAFIN", "direction": "LONG", "entry": 1799.2, "current": 1803.9, "pnl": 26.12, "ret_pct": 0.26, "logged_at": "2026-06-30"}, {"symbol": "PAYTM", "direction": "LONG", "entry": 1364.8, "current": 1368.0, "pnl": 23.45, "ret_pct": 0.23, "logged_at": "2026-07-15"}, {"symbol": "CHOLAFIN", "direction": "LONG", "entry": 1800.2, "current": 1803.9, "pnl": 20.55, "ret_pct": 0.21, "logged_at": "2026-07-03"}, {"symbol": "ICICIBANK", "direction": "LONG", "entry": 1413.3, "current": 1416.2, "pnl": 20.52, "ret_pct": 0.21, "logged_at": "2026-07-03"}, {"symbol": "KAJARIACER", "direction": "LONG", "entry": 1235.1, "current": 1237.0, "pnl": 15.38, "ret_pct": 0.15, "logged_at": "2026-07-14"}, {"symbol": "SONACOMS", "direction": "LONG", "entry": 668.35, "current": 669.2, "pnl": 12.72, "ret_pct": 0.13, "logged_at": "2026-07-14"}, {"symbol": "ABCAPITAL", "direction": "LONG", "entry": 403.85, "current": 404.3, "pnl": 11.14, "ret_pct": 0.11, "logged_at": "2026-07-03"}, {"symbol": "CHOLAFIN", "direction": "LONG", "entry": 1802.3, "current": 1803.9, "pnl": 8.88, "ret_pct": 0.09, "logged_at": "2026-07-02"}, {"symbol": "BAJFINANCE", "direction": "LONG", "entry": 1022.0, "current": 1021.3, "pnl": -6.85, "ret_pct": -0.07, "logged_at": "2026-07-02"}, {"symbol": "LAURUSLABS", "direction": "LONG", "entry": 1555.6, "current": 1554.3, "pnl": -8.36, "ret_pct": -0.08, "logged_at": "2026-07-13"}, {"symbol": "TATAELXSI", "direction": "SHORT", "entry": 3517.3, "current": 3520.4, "pnl": -8.81, "ret_pct": -0.09, "logged_at": "2026-07-15"}, {"symbol": "SONACOMS", "direction": "LONG", "entry": 670.0, "current": 669.2, "pnl": -11.94, "ret_pct": -0.12, "logged_at": "2026-07-13"}, {"symbol": "HFCL", "direction": "LONG", "entry": 223.41, "current": 223.08, "pnl": -14.77, "ret_pct": -0.15, "logged_at": "2026-07-15"}, {"symbol": "TITAN", "direction": "LONG", "entry": 4587.8, "current": 4579.4, "pnl": -18.31, "ret_pct": -0.18, "logged_at": "2026-07-07"}, {"symbol": "SUNPHARMA", "direction": "LONG", "entry": 1956.2, "current": 1951.5, "pnl": -24.03, "ret_pct": -0.24, "logged_at": "2026-07-15"}, {"symbol": "PAYTM", "direction": "LONG", "entry": 1373.0, "current": 1368.0, "pnl": -36.42, "ret_pct": -0.36, "logged_at": "2026-07-13"}, {"symbol": "LUPIN", "direction": "LONG", "entry": 2503.5, "current": 2493.0, "pnl": -41.94, "ret_pct": -0.42, "logged_at": "2026-07-15"}, {"symbol": "APOLLOHOSP", "direction": "LONG", "entry": 8977.5, "current": 8934.0, "pnl": -48.45, "ret_pct": -0.48, "logged_at": "2026-07-15"}, {"symbol": "LUPIN", "direction": "LONG", "entry": 2506.0, "current": 2493.0, "pnl": -51.88, "ret_pct": -0.52, "logged_at": "2026-07-08"}, {"symbol": "OFSS", "direction": "LONG", "entry": 11701.0, "current": 11625.0, "pnl": -64.95, "ret_pct": -0.65, "logged_at": "2026-07-15"}, {"symbol": "LAURUSLABS", "direction": "LONG", "entry": 1567.9, "current": 1554.3, "pnl": -86.74, "ret_pct": -0.87, "logged_at": "2026-07-14"}, {"symbol": "KAJARIACER", "direction": "LONG", "entry": 1248.0, "current": 1237.0, "pnl": -88.14, "ret_pct": -0.88, "logged_at": "2026-07-13"}, {"symbol": "BAJFINANCE", "direction": "LONG", "entry": 1030.4, "current": 1021.3, "pnl": -88.32, "ret_pct": -0.88, "logged_at": "2026-07-08"}, {"symbol": "SONACOMS", "direction": "LONG", "entry": 675.9, "current": 669.2, "pnl": -99.13, "ret_pct": -0.99, "logged_at": "2026-07-08"}, {"symbol": "BAJFINANCE", "direction": "LONG", "entry": 1034.5, "current": 1021.3, "pnl": -127.6, "ret_pct": -1.28, "logged_at": "2026-07-07"}, {"symbol": "EXIDEIND", "direction": "LONG", "entry": 426.0, "current": 419.2, "pnl": -159.62, "ret_pct": -1.6, "logged_at": "2026-07-09"}, {"symbol": "BAJFINANCE", "direction": "LONG", "entry": 1038.0, "current": 1021.3, "pnl": -160.89, "ret_pct": -1.61, "logged_at": "2026-07-03"}, {"symbol": "OFSS", "direction": "LONG", "entry": 11838.0, "current": 11625.0, "pnl": -179.93, "ret_pct": -1.8, "logged_at": "2026-07-14"}, {"symbol": "OFSS", "direction": "LONG", "entry": 11890.0, "current": 11625.0, "pnl": -222.88, "ret_pct": -2.23, "logged_at": "2026-07-13"}, {"symbol": "AUBANK", "direction": "LONG", "entry": 1064.8, "current": 1040.6, "pnl": -227.27, "ret_pct": -2.27, "logged_at": "2026-07-02"}, {"symbol": "AUBANK", "direction": "LONG", "entry": 1067.4, "current": 1040.6, "pnl": -251.08, "ret_pct": -2.51, "logged_at": "2026-07-06"}, {"symbol": "DELHIVERY", "direction": "LONG", "entry": 514.7, "current": 498.35, "pnl": -317.66, "ret_pct": -3.18, "logged_at": "2026-07-09"}, {"symbol": "DELHIVERY", "direction": "LONG", "entry": 515.05, "current": 498.35, "pnl": -324.24, "ret_pct": -3.24, "logged_at": "2026-07-06"}, {"symbol": "DELHIVERY", "direction": "LONG", "entry": 516.45, "current": 498.35, "pnl": -350.47, "ret_pct": -3.5, "logged_at": "2026-07-10"}, {"symbol": "DELHIVERY", "direction": "LONG", "entry": 520.1, "current": 498.35, "pnl": -418.19, "ret_pct": -4.18, "logged_at": "2026-07-07"}, {"symbol": "DLF", "direction": "LONG", "entry": 687.1, "current": 657.75, "pnl": -427.16, "ret_pct": -4.27, "logged_at": "2026-07-10"}], "closed": [{"symbol": "ZENSARTECH", "direction": "LONG", "entry": 539.75, "exit": 512.76, "pnl": -500.05, "ret_pct": -5.0, "outcome": "stop", "lived_up": false, "result": "stopped out", "logged_at": "2026-07-13"}, {"symbol": "MANAPPURAM", "direction": "LONG", "entry": 340.05, "exit": 323.05, "pnl": -499.93, "ret_pct": -5.0, "outcome": "stop", "lived_up": false, "result": "stopped out", "logged_at": "2026-07-10"}, {"symbol": "CHOLAFIN", "direction": "LONG", "entry": 1847.1, "exit": 1759.54, "pnl": -474.04, "ret_pct": -4.74, "outcome": "stop", "lived_up": false, "result": "stopped out", "logged_at": "2026-07-08"}, {"symbol": "HFCL", "direction": "LONG", "entry": 220.97, "exit": 209.92, "pnl": -500.07, "ret_pct": -5.0, "outcome": "stop", "lived_up": false, "result": "stopped out", "logged_at": "2026-07-08"}, {"symbol": "ETERNAL", "direction": "LONG", "entry": 294.75, "exit": 280.01, "pnl": -500.08, "ret_pct": -5.0, "outcome": "stop", "lived_up": false, "result": "stopped out", "logged_at": "2026-07-08"}, {"symbol": "CHOLAFIN", "direction": "LONG", "entry": 1846.6, "exit": 1755.89, "pnl": -491.23, "ret_pct": -4.91, "outcome": "stop", "lived_up": false, "result": "stopped out", "logged_at": "2026-07-07"}, {"symbol": "SHRIRAMFIN", "direction": "LONG", "entry": 1072.3, "exit": 1022.63, "pnl": -463.21, "ret_pct": -4.63, "outcome": "stop", "lived_up": false, "result": "stopped out", "logged_at": "2026-07-07"}, {"symbol": "HFCL", "direction": "LONG", "entry": 219.29, "exit": 208.33, "pnl": -499.79, "ret_pct": -5.0, "outcome": "stop", "lived_up": false, "result": "stopped out", "logged_at": "2026-07-07"}, {"symbol": "CHOLAFIN", "direction": "LONG", "entry": 1832.9, "exit": 1744.65, "pnl": -481.48, "ret_pct": -4.81, "outcome": "stop", "lived_up": false, "result": "stopped out", "logged_at": "2026-07-06"}, {"symbol": "ABCAPITAL", "direction": "LONG", "entry": 409.1, "exit": 388.89, "pnl": -494.01, "ret_pct": -4.94, "outcome": "stop", "lived_up": false, "result": "stopped out", "logged_at": "2026-07-06"}, {"symbol": "ICICIBANK", "direction": "LONG", "entry": 1426.0, "exit": 1378.29, "pnl": -334.57, "ret_pct": -3.35, "outcome": "stop", "lived_up": false, "result": "stopped out", "logged_at": "2026-07-06"}, {"symbol": "MANAPPURAM", "direction": "LONG", "entry": 344.8, "exit": 327.56, "pnl": -500.0, "ret_pct": -5.0, "outcome": "stop", "lived_up": false, "result": "stopped out", "logged_at": "2026-07-06"}, {"symbol": "SHRIRAMFIN", "direction": "LONG", "entry": 1074.5, "exit": 1025.39, "pnl": -457.05, "ret_pct": -4.57, "outcome": "stop", "lived_up": false, "result": "stopped out", "logged_at": "2026-07-03"}, {"symbol": "AUROPHARMA", "direction": "LONG", "entry": 1632.5, "exit": 1557.45, "pnl": -459.72, "ret_pct": -4.6, "outcome": "stop", "lived_up": false, "result": "stopped out", "logged_at": "2026-07-03"}, {"symbol": "MAXHEALTH", "direction": "LONG", "entry": 1156.0, "exit": 1098.2, "pnl": -500.0, "ret_pct": -5.0, "outcome": "stop", "lived_up": false, "result": "stopped out", "logged_at": "2026-07-03"}, {"symbol": "SHRIRAMFIN", "direction": "LONG", "entry": 1066.5, "exit": 1013.53, "pnl": -496.67, "ret_pct": -4.97, "outcome": "stop", "lived_up": false, "result": "stopped out", "logged_at": "2026-07-02"}, {"symbol": "FINCABLES", "direction": "LONG", "entry": 1145.9, "exit": 1088.61, "pnl": -499.96, "ret_pct": -5.0, "outcome": "stop", "lived_up": false, "result": "stopped out", "logged_at": "2026-07-02"}, {"symbol": "ONGC", "direction": "SHORT", "entry": 233.1, "exit": 244.76, "pnl": -500.21, "ret_pct": -5.0, "outcome": "stop", "lived_up": false, "result": "stopped out", "logged_at": "2026-06-30"}, {"symbol": "NATIONALUM", "direction": "SHORT", "entry": 332.15, "exit": 348.76, "pnl": -500.08, "ret_pct": -5.0, "outcome": "stop", "lived_up": false, "result": "stopped out", "logged_at": "2026-06-30"}, {"symbol": "SOUTHBANK", "direction": "LONG", "entry": 45.41, "exit": 43.14, "pnl": -499.89, "ret_pct": -5.0, "outcome": "stop", "lived_up": false, "result": "stopped out", "logged_at": "2026-06-29"}], "equity": [-25.73, -61.79, -11.18, -46.27, -546.16, -1046.37, -1546.45, -2043.12, -2543.08, -3000.13, -3459.85, -3959.85, -4441.33, -4935.34, -5269.91, -5769.91, -6261.14, -6724.35, -7224.14, -7698.18, -8198.25, -8698.33, -9198.26, -9698.31]}, "disclaimer": "EDUCATIONAL DECISION-SUPPORT ONLY - NOT FINANCIAL ADVICE. Signals are generated from delayed/free data and can be wrong. You are responsible for every trade. Never risk money you can't afford to lose."}